filmpy/Clip.py
filmpy/__init__.py
filmpy/config.py
filmpy/decorators.py
filmpy/editor.py
filmpy/tools.py
filmpy/utils.py
filmpy/version.py
filmpy/audio/AudioClip.py
filmpy/audio/__init__.py
filmpy/audio/fx/__init__.py
filmpy/audio/fx/audio_delay.py
filmpy/audio/fx/audio_fadein.py
filmpy/audio/fx/audio_fadeout.py
filmpy/audio/fx/audio_loop.py
filmpy/audio/fx/audio_normalize.py
filmpy/audio/fx/multiply_stereo_volume.py
filmpy/audio/fx/multiply_volume.py
filmpy/audio/io/AudioFileClip.py
filmpy/audio/io/__init__.py
filmpy/audio/io/ffmpeg_audiowriter.py
filmpy/audio/io/preview.py
filmpy/audio/io/readers.py
filmpy/audio/tools/__init__.py
filmpy/audio/tools/cuts.py
filmpy/video/VideoClip.py
filmpy/video/__init__.py
filmpy/video/compositing/CompositeVideoClip.py
filmpy/video/compositing/__init__.py
filmpy/video/compositing/concatenate.py
filmpy/video/compositing/transitions.py
filmpy/video/fx/__init__.py
filmpy/video/fx/accel_decel.py
filmpy/video/fx/blackwhite.py
filmpy/video/fx/blink.py
filmpy/video/fx/crop.py
filmpy/video/fx/even_size.py
filmpy/video/fx/fadein.py
filmpy/video/fx/fadeout.py
filmpy/video/fx/freeze.py
filmpy/video/fx/freeze_region.py
filmpy/video/fx/gamma_corr.py
filmpy/video/fx/headblur.py
filmpy/video/fx/invert_colors.py
filmpy/video/fx/loop.py
filmpy/video/fx/lum_contrast.py
filmpy/video/fx/make_loopable.py
filmpy/video/fx/margin.py
filmpy/video/fx/mask_and.py
filmpy/video/fx/mask_color.py
filmpy/video/fx/mask_or.py
filmpy/video/fx/mirror_x.py
filmpy/video/fx/mirror_y.py
filmpy/video/fx/multiply_color.py
filmpy/video/fx/multiply_speed.py
filmpy/video/fx/painting.py
filmpy/video/fx/resize.py
filmpy/video/fx/rotate.py
filmpy/video/fx/scroll.py
filmpy/video/fx/supersample.py
filmpy/video/fx/time_mirror.py
filmpy/video/fx/time_symmetrize.py
filmpy/video/io/ImageSequenceClip.py
filmpy/video/io/VideoFileClip.py
filmpy/video/io/__init__.py
filmpy/video/io/bindings.py
filmpy/video/io/downloader.py
filmpy/video/io/ffmpeg_reader.py
filmpy/video/io/ffmpeg_tools.py
filmpy-0.1.2.dist-info/METADATA
filmpy-0.1.2.dist-info/WHEEL
filmpy-0.1.2.dist-info/licenses/LICENSE.md
filmpy-0.1.2.dist-info/RECORD
